spol/__init__.py
spol/spol.py
spol-0.0.1.dist-info/METADATA
spol-0.0.1.dist-info/WHEEL
spol-0.0.1.dist-info/top_level.txt
spol-0.0.1.dist-info/RECORD
