Metadata-Version: 2.1
Name: spol
Version: 0.0.1
Summary: Pakistan Sindh Police
Author: siphr
Author-email: pypi@techtum.dev
Project-URL: Homepage, https://www.techtum.dev/work-spcs-220121.html#work-spol-220121
Project-URL: Source, https://github.com/siphr/spol
Project-URL: Tracker, https://github.com/siphr/spol/issues
Keywords: pakistan,sindh,police,complaint,query,search,units
Platform: any
